macode/__init__.py
macode/dataset.py
macode/macode.py
macode/missing.py
macode/model.py
macode-1.0.1.dist-info/LICENSE
macode-1.0.1.dist-info/METADATA
macode-1.0.1.dist-info/WHEEL
macode-1.0.1.dist-info/RECORD
