Metadata-Version: 2.3
Name: macode
Version: 1.0.1
Summary: Package for Implementing MaCoDE
License: MIT
Author: an-seunghwan
Author-email: dpeltms79@gmail.com
Requires-Python: >=3.10,<4.0
Classifier: License :: OSI Approved :: MIT License
Classifier: Programming Language :: Python :: 3
Classifier: Programming Language :: Python :: 3.10
Classifier: Programming Language :: Python :: 3.11
Classifier: Programming Language :: Python :: 3.12
Classifier: Programming Language :: Python :: 3.13
Requires-Dist: geomloss (==0.2.6)
Requires-Dist: matplotlib (==3.10.0)
Requires-Dist: numpy (==1.26.4)
Requires-Dist: pandas (==2.2.3)
Requires-Dist: pillow (==11.0.0)
Requires-Dist: scikit-learn (==1.6.0)
Requires-Dist: scipy (==1.14.1)
Requires-Dist: seaborn (==0.13.2)
Requires-Dist: statsmodels (==0.14.4)
Requires-Dist: torch (==2.2.2)
Requires-Dist: tqdm (==4.66.4)
Requires-Dist: wandb (==0.19.1)
